hellonlp/__init__.py
hellonlp/ChineseWordSegmentation/__init__.py
hellonlp/ChineseWordSegmentation/discovery_word.py
hellonlp/ChineseWordSegmentation/hyperparameters.py
hellonlp/ChineseWordSegmentation/modules.py
hellonlp/ChineseWordSegmentation/probability.py
hellonlp/ChineseWordSegmentation/segment_entropy.py
hellonlp/ChineseWordSegmentation/tokenization.py
hellonlp/ChineseWordSegmentation/utils.py
hellonlp/ChineseWordSegmentation/dict/vocabulary.txt
hellonlp/ChineseWordSegmentation/dict/vocabulary_word.txt
hellonlp-0.2.41.dist-info/METADATA
hellonlp-0.2.41.dist-info/RECORD
hellonlp-0.2.41.dist-info/WHEEL
hellonlp-0.2.41.dist-info/top_level.txt
